[{
    "id": 1,
    "price": 1000,
    "title": "Филадельфия",
    "image": "assets/1.png"

},

{
    "id": 2,
    "price": 1500,
    "title": "Угорь",
    "image": "assets/1.png"
},

{
    "id": 3,
    "price": 2000,
    "title": "Маки",
    "image": "assets/1.png"
},

{
    "id": 4,
    "price": 1450,
    "title": "Лосось",
    "image": "assets/1.png"
},

{
    "id": 5,
    "price": 1399,
    "title": "Запеченные мидии",
    "image": "assets/1.png"
},

{
    "id": 6,
    "price": 1200,
    "title": "Запеченный ласось",
    "image": "assets/1.png"

}]
